promptron/__init__.py
promptron/config_helper.py
promptron/llm_config.py
promptron/prompt_generator.py
promptron/config/.env.example
promptron/config/config.yml
promptron/prompt_templates/prompt_template.json
promptron/services/__init__.py
promptron/services/llm_service.py
promptron-1.0.1.dist-info/licenses/LICENSE
promptron-1.0.1.dist-info/METADATA
promptron-1.0.1.dist-info/WHEEL
promptron-1.0.1.dist-info/top_level.txt
promptron-1.0.1.dist-info/RECORD
