Metadata-Version: 2.4
Name: promptron
Version: 1.0.1
Summary: A Python package for generating evaluation datasets using LLMs
Author-email: Hit Shiroya <24.hiit@gmail.com>
License: MIT
Keywords: llm,prompt-generation,dataset,evaluation,ollama
Classifier: Development Status :: 3 - Alpha
Classifier: Intended Audience :: Developers
Classifier: License :: OSI Approved :: MIT License
Classifier: Programming Language :: Python :: 3
Classifier: Programming Language :: Python :: 3.8
Classifier: Programming Language :: Python :: 3.9
Classifier: Programming Language :: Python :: 3.10
Classifier: Programming Language :: Python :: 3.11
Requires-Python: >=3.8
License-File: LICENSE
Requires-Dist: langchain-ollama>=0.1.0
Requires-Dist: pyyaml>=6.0
Requires-Dist: python-dotenv>=1.0.0
Provides-Extra: openai
Requires-Dist: langchain-openai>=0.1.0; extra == "openai"
Provides-Extra: anthropic
Requires-Dist: langchain-anthropic>=0.1.0; extra == "anthropic"
Provides-Extra: dev
Requires-Dist: pytest>=7.0; extra == "dev"
Requires-Dist: black>=23.0; extra == "dev"
Requires-Dist: flake8>=6.0; extra == "dev"
Dynamic: license-file
